neptune_fetcher/__init__.py
neptune_fetching_api-0.0.1a4.dist-info/METADATA
neptune_fetching_api-0.0.1a4.dist-info/WHEEL
neptune_fetching_api-0.0.1a4.dist-info/RECORD
